es3_modifier/__init__.py
es3_modifier/main.py
es3_modifier-0.1.0.dist-info/LICENSE
es3_modifier-0.1.0.dist-info/METADATA
es3_modifier-0.1.0.dist-info/WHEEL
es3_modifier-0.1.0.dist-info/entry_points.txt
es3_modifier-0.1.0.dist-info/top_level.txt
es3_modifier-0.1.0.dist-info/RECORD
