Metadata-Version: 2.1
Name: es3-modifier
Version: 0.1.0
Summary: A package to decrypt, edit and encrypt EasySave files used in Unity games
Home-page: https://github.com/crtdll/es3-modifier
Author: crtdll
License-File: LICENSE
Requires-Dist: pycryptodome
